epispot/__init__.py
epispot/comps.py
epispot/fitters.py
epispot/models.py
epispot/plots.py
epispot/pre.py
epispot-2.1.1.dist-info/LICENSE
epispot-2.1.1.dist-info/METADATA
epispot-2.1.1.dist-info/WHEEL
epispot-2.1.1.dist-info/top_level.txt
epispot-2.1.1.dist-info/RECORD
