Metadata-Version: 2.1
Name: epispot
Version: 2.1.1
Summary: A tool for modeling infectious diseases.
Home-page: https://www.github.com/epispot/epispot
Author: quantum9innovation
License: UNKNOWN
Platform: UNKNOWN
Classifier: Programming Language :: Python :: 3.7
Classifier: License :: OSI Approved :: GNU General Public License v3 (GPLv3)
Classifier: Operating System :: OS Independent
Requires-Python: >=3.7
Requires-Dist: matplotlib
Requires-Dist: numpy
